napari_manual_classifier/__init__.py
napari_manual_classifier/_version.py
napari_manual_classifier/napari_manual_classifier.py
napari_manual_classifier/_tests/__init__.py
napari_manual_classifier/_tests/test_classifier.py
napari_manual_classifier-0.1.dev21.dist-info/LICENSE
napari_manual_classifier-0.1.dev21.dist-info/METADATA
napari_manual_classifier-0.1.dev21.dist-info/WHEEL
napari_manual_classifier-0.1.dev21.dist-info/entry_points.txt
napari_manual_classifier-0.1.dev21.dist-info/top_level.txt
napari_manual_classifier-0.1.dev21.dist-info/RECORD
