Metadata-Version: 2.1
Name: napari-manual-classifier
Version: 0.1.dev21
Summary: Simple napari widget for manually annotating classes for each slice (last 2 dimensions) of ND-image
Home-page: https://github.com/lukebfunk/napari-manual-classifier
Author: Luke Funk
Author-email: lukefunk@broadinstitute.org
License: MIT
Platform: UNKNOWN
Classifier: Development Status :: 4 - Beta
Classifier: Intended Audience :: Developers
Classifier: Topic :: Software Development :: Testing
Classifier: Programming Language :: Python
Classifier: Programming Language :: Python :: 3
Classifier: Programming Language :: Python :: 3.6
Classifier: Programming Language :: Python :: 3.7
Classifier: Programming Language :: Python :: 3.8
Classifier: Programming Language :: Python :: Implementation :: CPython
Classifier: Programming Language :: Python :: Implementation :: PyPy
Classifier: Operating System :: OS Independent
Classifier: License :: OSI Approved :: MIT License
Requires-Python: >=3.6
Requires-Dist: qtpy
Requires-Dist: napari
Requires-Dist: pandas
